caption/__init__.py
caption/caption_engine.py
caption/cli_main.py
caption/cli_parser.py
caption/manifest.json
caption/utils.py
zz_img_caption-0.0.3.dist-info/METADATA
zz_img_caption-0.0.3.dist-info/WHEEL
zz_img_caption-0.0.3.dist-info/entry_points.txt
zz_img_caption-0.0.3.dist-info/top_level.txt
zz_img_caption-0.0.3.dist-info/RECORD
